telomerehunter2/TVR_context.py
telomerehunter2/TVR_context_summary_tables.py
telomerehunter2/TVR_screen.py
telomerehunter2/__init__.py
telomerehunter2/estimate_telomere_content.py
telomerehunter2/fast_mode.py
telomerehunter2/filter_telomere_reads.py
telomerehunter2/get_repeat_threshold.py
telomerehunter2/get_summed_intratelomeric_read_length.py
telomerehunter2/merge_pdfs.py
telomerehunter2/normalize_TVR_counts.py
telomerehunter2/plot_functions.py
telomerehunter2/repeat_frequency_intratelomeric.py
telomerehunter2/sort_telomere_reads.py
telomerehunter2/telomerehunter2_main.py
telomerehunter2/telomerehunter2_sc.py
telomerehunter2/utils.py
telomerehunter2/cytoband_files/T2T_chm13v2.0_cytoBand.txt
telomerehunter2/cytoband_files/cytoBand_dog.txt
telomerehunter2/cytoband_files/hg19_cytoBand.txt
telomerehunter2/cytoband_files/hg38_cytoBand.txt
telomerehunter2-1.0.5.dist-info/licenses/LICENSE.txt
telomerehunter2-1.0.5.dist-info/METADATA
telomerehunter2-1.0.5.dist-info/WHEEL
telomerehunter2-1.0.5.dist-info/entry_points.txt
telomerehunter2-1.0.5.dist-info/top_level.txt
telomerehunter2-1.0.5.dist-info/RECORD
