Metadata-Version: 2.4
Name: telomerehunter2
Version: 1.0.5
Summary: An advanced version of TelomereHunter for Python 3, with new features
Author: LS
Author-email: FP <f.popp@dkfz.de>, LF <l.feuerbach@dkfz.de>
License:                     GNU GENERAL PUBLIC LICENSE
Project-URL: homepage, https://www.dkfz.de/angewandte-bioinformatik/telomerehunter
Project-URL: repository, https://github.com/ferdinand-popp/telomerehunter2
Project-URL: documentation, https://github.com/ferdinand-popp/telomerehunter2#readme
Keywords: telomere content,read,NGS,WGS,tumor control
Classifier: Development Status :: 3 - Alpha
Classifier: Topic :: Scientific/Engineering :: Bio-Informatics
Classifier: License :: OSI Approved :: GNU General Public License v3 or later (GPLv3+)
Classifier: Programming Language :: Python :: 3
Classifier: Programming Language :: Python :: 3.8
Classifier: Programming Language :: Python :: 3.9
Classifier: Programming Language :: Python :: 3.10
Classifier: Programming Language :: Python :: 3.11
Classifier: Programming Language :: Python :: 3.12
Classifier: Programming Language :: Python :: 3.13
Classifier: Programming Language :: Python :: 3.14
Requires-Python: >=3.8
License-File: LICENSE.txt
Requires-Dist: pysam>=0.20.0
Requires-Dist: pandas>=1.4.0
Requires-Dist: numpy>=1.22.0
Requires-Dist: PyPDF2>=2.0.0
Requires-Dist: plotly>=5.0.0
Requires-Dist: kaleido>=0.2.1
Provides-Extra: dev
Requires-Dist: ruff>=0.1.6; extra == "dev"
Requires-Dist: tox>=4.0.0; extra == "dev"
Dynamic: license-file
